deezloadclone-2024.5.5.data/scripts/deez-dw.py
deezloadclone-2024.5.5.data/scripts/deez-web.py
deezloader/__init__.py
deezloader/__taggers__.py
deezloader/easy_spoty.py
deezloader/exceptions.py
deezloader/deezloader/__download__.py
deezloader/deezloader/__download_utils__.py
deezloader/deezloader/__init__.py
deezloader/deezloader/__utils__.py
deezloader/deezloader/dee_api.py
deezloader/deezloader/deegw_api.py
deezloader/deezloader/deezer_settings.py
deezloader/libutils/__init__.py
deezloader/libutils/others_settings.py
deezloader/libutils/utils.py
deezloader/models/__init__.py
deezloader/models/album.py
deezloader/models/episode.py
deezloader/models/playlist.py
deezloader/models/preferences.py
deezloader/models/smart.py
deezloader/models/track.py
deezloader/spotloader/__download__.py
deezloader/spotloader/__init__.py
deezloader/spotloader/__spo_api__.py
deezloader/spotloader/podcastspo.py
deezloader/spotloader/spotify_settings.py
deezloadclone-2024.5.5.dist-info/LICENSE
deezloadclone-2024.5.5.dist-info/METADATA
deezloadclone-2024.5.5.dist-info/WHEEL
deezloadclone-2024.5.5.dist-info/top_level.txt
deezloadclone-2024.5.5.dist-info/RECORD
