Metadata-Version: 2.1
Name: deezloadclone
Version: 2024.5.5
Summary: Downloads songs, albums or playlists from deezer and spotify (cloned from https://github.com/An0nimia/deezloader)
Home-page: https://github.com/farihdzkyy/deezloadclone
Author: farihdzaky
Author-email: farihdzakyy@gmail.com
License: GNU Affero General Public License v3
Requires-Python: >=3.10
License-File: LICENSE
Requires-Dist: mutagen
Requires-Dist: pycryptodome
Requires-Dist: requests
Requires-Dist: spotipy
Requires-Dist: tqdm
Requires-Dist: fastapi
Requires-Dist: uvicorn[standard]
Requires-Dist: librespot
